{
"joints" : [
    {   "name" : "HeadYaw",
        "type"   : "revolute",
        "parent" : "torso",
        "child"  : "Neck",
        "xyz"    : [0,0,0.1265],
        "rpy"    : [0,0,0],
        "axis"   : [0,0,1.0],
        "limits" : [-2.08567,2.08567]    },
    {   "name"   : "HeadPitch",
        "type"   : "revolute",
        "parent" : "Neck",
        "child"  : "Head",
        "xyz"    : [0,0,0],
        "rpy"    : [0,0,0],
        "axis"   : [0,1.0,0],
        "limits" : [-0.671952,0.514872]    },
    {   "name"   : "gaze_joint",
        "type"   : "fixed",
        "parent" : "Head",
        "child"  : "gaze",
        "xyz"    : [0.05871,0,0.06364],
        "rpy"    : [0,0,0],
        "axis"   : [0,0,0],
        "limits" : [-3.141592653589793,3.141592653589793]    },
    {   "name"   : "LHipYawPitch",
        "type"   : "revolute",
        "parent" : "torso",
        "child"  : "LPelvis",
        "xyz"    : [0,0.05,-0.085],
        "rpy"    : [0,0,0],
        "axis"   : [0,0.707106,-0.707106],
        "limits" : [-1.14529,0.740718]    },
    {   "name"   : "LHipRoll",
        "type"   : "revolute",
        "parent" : "LPelvis",
        "child"  : "LHip",
        "xyz"    : [0,0,0],
        "rpy"    : [0,0,0],
        "axis"   : [1.0,0,0],
        "limits" : [-0.379435,0.79046]    },
    {   "name"   : "LHipPitch",
        "type"   : "revolute",
        "parent" : "LHip",
        "child"  : "LThigh",
        "xyz"    : [0,0,0],
        "rpy"    : [0,0,0],
        "axis"   : [0,1.0,0],
        "limits" : [-1.53589,0.48398]    },
    {   "name"   : "LKneePitch",
        "type"   : "revolute",
        "parent" : "LThigh",
        "child"  : "LTibia",
        "xyz"    : [0,0,-0.1],
        "rpy"    : [0,0,0],
        "axis"   : [0,1.0,0],
        "limits" : [-0.0923279,2.11255]    },
    {   "name"   : "LAnklePitch",
        "type"   : "revolute",
        "parent" : "LTibia",
        "child"  : "LAnklePitch",
        "xyz"    : [0,0,-0.1029],
        "rpy"    : [0,0,0],
        "axis"   : [0,1.0,0],
        "limits" : [-1.18944,0.922581]    },
    {   "name"   : "LAnkleRoll",
        "type"   : "revolute",
        "parent" : "LAnklePitch",
        "child"  : "l_ankle",
        "xyz"    : [0,0,0],
        "rpy"    : [0,0,0],
        "axis"   : [1.0,0,0],
        "limits" : [-0.397761,0.768992]    },
    {   "name"   : "LLeg_effector_fixedjoint",
        "type"   : "fixed",
        "parent" : "l_ankle",
        "child"  : "l_sole",
        "xyz"    : [0,0,-0.04511],
        "rpy"    : [0,0,0],
        "axis"   : [0,0,0],
        "limits" : [-3.141592653589793,3.141592653589793]    },
    {   "name"   : "RHipYawPitch",
        "type"   : "revolute",
        "parent" : "torso",
        "child"  : "RPelvis",
        "xyz"    : [0,-0.05,-0.085],
        "rpy"    : [0,0,0],
        "axis"   : [0,0.707106,0.707106],
        "limits" : [-1.14529,0.740718]    },
    {   "name"   : "RHipRoll",
        "type"   : "revolute",
        "parent" : "RPelvis",
        "child"  : "RHip",
        "xyz"    : [0,0,0],
        "rpy"    : [0,0,0],
        "axis"   : [1.0,0,0],
        "limits" : [-0.79046,0.379435]    },
    {   "name"   : "RHipPitch",
        "type"   : "revolute",
        "parent" : "RHip",
        "child"  : "RThigh",
        "xyz"    : [0,0,0],
        "rpy"    : [0,0,0],
        "axis"   : [0,1.0,0],
        "limits" : [-1.53589,0.48398]    },
    {   "name"   : "RKneePitch",
        "type"   : "revolute",
        "parent" : "RThigh",
        "child"  : "RTibia",
        "xyz"    : [0,0,-0.1],
        "rpy"    : [0,0,0],
        "axis"   : [0,1.0,0],
        "limits" : [-0.0923279,2.11255]    },
    {   "name"   : "RAnklePitch",
        "type"   : "revolute",
        "parent" : "RTibia",
        "child"  : "RAnklePitch",
        "xyz"    : [0,0,-0.1029],
        "rpy"    : [0,0,0],
        "axis"   : [0,1.0,0],
        "limits" : [-1.1863,0.932006]    },
    {   "name"   : "RAnkleRoll",
        "type"   : "revolute",
        "parent" : "RAnklePitch",
        "child"  : "r_ankle",
        "xyz"    : [0,0,0],
        "rpy"    : [0,0,0],
        "axis"   : [1.0,0,0],
        "limits" : [-0.768992,0.397761]    },
    {   "name"   : "RLeg_effector_fixedjoint",
        "type"   : "fixed",
        "parent" : "r_ankle",
        "child"  : "r_sole",
        "xyz"    : [0,0,-0.04511],
        "rpy"    : [0,0,0],
        "axis"   : [0,0,0],
        "limits" : [-3.141592653589793,3.141592653589793]    },
    {   "name"   : "base_link_fixedjoint",
        "type"   : "fixed",
        "parent" : "base_link",
        "child"  : "torso",
        "xyz"    : [0,0,0],
        "rpy"    : [0,0,0],
        "axis"   : [0,0,0],
        "limits" : [-3.141592653589793,3.141592653589793]    },
    {   "name"   : "LShoulderPitch",
        "type"   : "revolute",
        "parent" : "torso",
        "child"  : "LShoulder",
        "xyz"    : [0,0.098,0.1],
        "rpy"    : [0,0,0],
        "axis"   : [0,1.0,0],
        "limits" : [-2.08567,2.08567]    },
    {   "name"   : "LShoulderRoll",
        "type"   : "revolute",
        "parent" : "LShoulder",
        "child"  : "LBicep",
        "xyz"    : [0,0,0],
        "rpy"    : [0,0,0],
        "axis"   : [0,0,1.0],
        "limits" : [-0.314159,1.32645]    },
    {   "name"   : "LElbowYaw",
        "type"   : "revolute",
        "parent" : "LBicep",
        "child"  : "LElbow",
        "xyz"    : [0.105,0.015,0],
        "rpy"    : [0,0,0],
        "axis"   : [1.0,0,0],
        "limits" : [-2.08567,2.08567]    },
    {   "name"   : "LElbowRoll",
        "type"   : "revolute",
        "parent" : "LElbow",
        "child"  : "LForeArm",
        "xyz"    : [0,0,0],
        "rpy"    : [0,0,0],
        "axis"   : [0,0,1.0],
        "limits" : [-1.54462,-0.0349066]    },
    {   "name"   : "LWristYaw",
        "type"   : "revolute",
        "parent" : "LForeArm",
        "child"  : "l_wrist",
        "xyz"    : [0.05595,0,0],
        "rpy"    : [0,0,0],
        "axis"   : [1.0,0,0],
        "limits" : [-1.82387,1.82387]    },
    {   "name"   : "LHand",
        "type"   : "revolute",
        "parent" : "l_wrist",
        "child"  : "l_gripper",
        "xyz"    : [0.05775,0,-0.01231],
        "rpy"    : [0,0,0],
        "axis"   : [1.0,0,0],
        "limits" : [0,1.0]    },
    {   "name"   : "RShoulderPitch",
        "type"   : "revolute",
        "parent" : "torso",
        "child"  : "RShoulder",
        "xyz"    : [0,-0.098,0.1],
        "rpy"    : [0,0,0],
        "axis"   : [0,1.0,0],
        "limits" : [-2.08567,2.08567]    },
    {   "name"   : "RShoulderRoll",
        "type"   : "revolute",
        "parent" : "RShoulder",
        "child"  : "RBicep",
        "xyz"    : [0,0,0],
        "rpy"    : [0,0,0],
        "axis"   : [0,0,1.0],
        "limits" : [-1.32645,0.314159]    },
    {   "name"   : "RElbowYaw",
        "type"   : "revolute",
        "parent" : "RBicep",
        "child"  : "RElbow",
        "xyz"    : [0.105,-0.015,0],
        "rpy"    : [0,0,0],
        "axis"   : [1.0,0,0],
        "limits" : [-2.08567,2.08567]    },
    {   "name"   : "RElbowRoll",
        "type"   : "revolute",
        "parent" : "RElbow",
        "child"  : "RForeArm",
        "xyz"    : [0,0,0],
        "rpy"    : [0,0,0],
        "axis"   : [0,0,1.0],
        "limits" : [0.0349066,1.54462]    },
    {   "name"   : "RWristYaw",
        "type"   : "revolute",
        "parent" : "RForeArm",
        "child"  : "r_wrist",
        "xyz"    : [0.05595,0,0],
        "rpy"    : [0,0,0],
        "axis"   : [1.0,0,0],
        "limits" : [-1.82387,1.82387]    },
    {   "name"   : "RHand",
        "type"   : "revolute",
        "parent" : "r_wrist",
        "child"  : "r_gripper",
        "xyz"    : [0.05775,0,-0.01213],
        "rpy"    : [0,0,0],
        "axis"   : [1.0,0,0],
        "limits" : [0,1.0]    },
    {   "name"   : "LFoot/Bumper/Right_sensor_fixedjoint",
        "type"   : "fixed",
        "parent" : "l_ankle",
        "child"  : "LFootBumperRight_frame",
        "xyz"    : [0.0876,-0.014,-0.0353],
        "rpy"    : [0,0,0],
        "axis"   : [0,0,0],
        "limits" : [-3.141592653589793,3.141592653589793]    },
    {   "name"   : "RFoot/FSR/RearLeft_sensor_fixedjoint",
        "type"   : "fixed",
        "parent" : "r_ankle",
        "child"  : "RFsrRL_frame",
        "xyz"    : [-0.03025,0.0191,-0.04511],
        "rpy"    : [0,0,0],
        "axis"   : [0,0,0],
        "limits" : [-3.141592653589793,3.141592653589793]    },
    {   "name"   : "CameraBottom_optical_frame_fixedjoint",
        "type"   : "fixed",
        "parent" : "CameraBottom_frame",
        "child"  : "CameraBottom_optical_frame",
        "xyz"    : [0,0,0],
        "rpy"    : [-1.57079632679,0,-1.57079632679],
        "axis"   : [0,0,0],
        "limits" : [-3.141592653589793,3.141592653589793]    },
    {   "name"   : "RFoot/FSR/RearRight_sensor_fixedjoint",
        "type"   : "fixed",
        "parent" : "r_ankle",
        "child"  : "RFsrRR_frame",
        "xyz"    : [-0.02965,-0.0299,-0.04511],
        "rpy"    : [0,0,0],
        "axis"   : [0,0,0],
        "limits" : [-3.141592653589793,3.141592653589793]    },
    {   "name"   : "LFoot/FSR/FrontRight_sensor_fixedjoint",
        "type"   : "fixed",
        "parent" : "l_ankle",
        "child"  : "LFsrFR_frame",
        "xyz"    : [0.07025,-0.0231,-0.04511],
        "rpy"    : [0,0,0],
        "axis"   : [0,0,0],
        "limits" : [-3.141592653589793,3.141592653589793]    },
    {   "name"   : "LHand/Touch/Left_sensor_fixedjoint",
        "type"   : "fixed",
        "parent" : "l_wrist",
        "child"  : "LHandTouchLeft_frame",
        "xyz"    : [0.032,0.025,0.003],
        "rpy"    : [0,0,1.5708],
        "axis"   : [0,0,0],
        "limits" : [-3.141592653589793,3.141592653589793]    },
    {   "name"   : "RFoot/Bumper/Right_sensor_fixedjoint",
        "type"   : "fixed",
        "parent" : "r_ankle",
        "child"  : "RFootBumperRight_frame",
        "xyz"    : [0.0876,-0.019,-0.0353],
        "rpy"    : [0,0,0],
        "axis"   : [0,0,0],
        "limits" : [-3.141592653589793,3.141592653589793]    },
    {   "name"   : "RFoot/FSR/FrontRight_sensor_fixedjoint",
        "type"   : "fixed",
        "parent" : "r_ankle",
        "child"  : "RFsrFR_frame",
        "xyz"    : [0.07025,-0.0299,-0.04511],
        "rpy"    : [0,0,0],
        "axis"   : [0,0,0],
        "limits" : [-3.141592653589793,3.141592653589793]    },
    {   "name"   : "LFoot/FSR/RearRight_sensor_fixedjoint",
        "type"   : "fixed",
        "parent" : "l_ankle",
        "child"  : "LFsrRR_frame",
        "xyz"    : [-0.02965,-0.0191,-0.04511],
        "rpy"    : [0,0,0],
        "axis"   : [0,0,0],
        "limits" : [-3.141592653589793,3.141592653589793]    },
    {   "name"   : "Accelerometer_sensor_fixedjoint",
        "type"   : "fixed",
        "parent" : "torso",
        "child"  : "ImuTorsoAccelerometer_frame",
        "xyz"    : [-0.008,0.00606,0.027],
        "rpy"    : [0,0,0],
        "axis"   : [0,0,0],
        "limits" : [-3.141592653589793,3.141592653589793]    },
    {   "name"   : "Head/Touch/Front_sensor_fixedjoint",
        "type"   : "fixed",
        "parent" : "Head",
        "child"  : "HeadTouchFront_frame",
        "xyz"    : [0.0312,0,0.1014],
        "rpy"    : [0,-1.1861,0],
        "axis"   : [0,0,0],
        "limits" : [-3.141592653589793,3.141592653589793]    },
    {   "name"   : "RFoot/Bumper/Left_sensor_fixedjoint",
        "type"   : "fixed",
        "parent" : "r_ankle",
        "child"  : "RFootBumperLeft_frame",
        "xyz"    : [0.0876,0.014,-0.0353],
        "rpy"    : [0,0,0],
        "axis"   : [0,0,0],
        "limits" : [-3.141592653589793,3.141592653589793]    },
    {   "name"   : "Sonar/Right_sensor_fixedjoint",
        "type"   : "fixed",
        "parent" : "torso",
        "child"  : "RSonar_frame",
        "xyz"    : [0.00558253,-0.0192068,0.0623853],
        "rpy"    : [0.00478508,0.0436497,-0.392441],
        "axis"   : [0,0,0],
        "limits" : [-3.141592653589793,3.141592653589793]    },
    {   "name"   : "RHand/Touch/Right_sensor_fixedjoint",
        "type"   : "fixed",
        "parent" : "r_wrist",
        "child"  : "RHandTouchRight_frame",
        "xyz"    : [0.035,-0.025,0.0035],
        "rpy"    : [0,0,-1.5708],
        "axis"   : [0,0,0],
        "limits" : [-3.141592653589793,3.141592653589793]    },
    {   "name"   : "RHand/Touch/Back_sensor_fixedjoint",
        "type"   : "fixed",
        "parent" : "r_wrist",
        "child"  : "RHandTouchBack_frame",
        "xyz"    : [0.038,0,0.025],
        "rpy"    : [3.14159,-1.5708,3.14159],
        "axis"   : [0,0,0],
        "limits" : [-3.141592653589793,3.141592653589793]    },
    {   "name"   : "RFoot/FSR/FrontLeft_sensor_fixedjoint",
        "type"   : "fixed",
        "parent" : "r_ankle",
        "child"  : "RFsrFL_frame",
        "xyz"    : [0.07025,0.0231,-0.04511],
        "rpy"    : [0,0,0],
        "axis"   : [0,0,0],
        "limits" : [-3.141592653589793,3.141592653589793]    },
    {   "name"   : "Sonar/Left_sensor_fixedjoint",
        "type"   : "fixed",
        "parent" : "torso",
        "child"  : "LSonar_frame",
        "xyz"    : [0.00558253,0.0192068,0.0623853],
        "rpy"    : [-0.00478508,0.0436497,0.392441],
        "axis"   : [0,0,0],
        "limits" : [-3.141592653589793,3.141592653589793]    },
    {   "name"   : "LFoot/FSR/FrontLeft_sensor_fixedjoint",
        "type"   : "fixed",
        "parent" : "l_ankle",
        "child"  : "LFsrFL_frame",
        "xyz"    : [0.07025,0.0299,-0.04511],
        "rpy"    : [0,0,0],
        "axis"   : [0,0,0],
        "limits" : [-3.141592653589793,3.141592653589793]    },
    {   "name"   : "LFoot/FSR/RearLeft_sensor_fixedjoint",
        "type"   : "fixed",
        "parent" : "l_ankle",
        "child"  : "LFsrRL_frame",
        "xyz"    : [-0.03025,0.0299,-0.04511],
        "rpy"    : [0,0,0],
        "axis"   : [0,0,0],
        "limits" : [-3.141592653589793,3.141592653589793]    },
    {   "name"   : "RHand/Touch/Left_sensor_fixedjoint",
        "type"   : "fixed",
        "parent" : "r_wrist",
        "child"  : "RHandTouchLeft_frame",
        "xyz"    : [0.032,0.025,0.003],
        "rpy"    : [0,0,1.5708],
        "axis"   : [0,0,0],
        "limits" : [-3.141592653589793,3.141592653589793]    },
    {   "name"   : "CameraBottom_sensor_fixedjoint",
        "type"   : "fixed",
        "parent" : "Head",
        "child"  : "CameraBottom_frame",
        "xyz"    : [0.05071,0,0.01774],
        "rpy"    : [0,0.692896,0],
        "axis"   : [0,0,0],
        "limits" : [-3.141592653589793,3.141592653589793]    },
    {   "name"   : "CameraTop_sensor_fixedjoint",
        "type"   : "fixed",
        "parent" : "Head",
        "child"  : "CameraTop_frame",
        "xyz"    : [0.05871,0,0.06364],
        "rpy"    : [0,0.0209435,0],
        "axis"   : [0,0,0],
        "limits" : [-3.141592653589793,3.141592653589793]    },
    {   "name"   : "CameraTop_optical_frame_fixedjoint",
        "type"   : "fixed",
        "parent" : "CameraTop_frame",
        "child"  : "CameraTop_optical_frame",
        "xyz"    : [0,0,0],
        "rpy"    : [-1.57079632679,0,-1.57079632679],
        "axis"   : [0,0,0],
        "limits" : [-3.141592653589793,3.141592653589793]    },
    {   "name"   : "LHand/Touch/Back_sensor_fixedjoint",
        "type"   : "fixed",
        "parent" : "l_wrist",
        "child"  : "LHandTouchBack_frame",
        "xyz"    : [0.038,0,0.025],
        "rpy"    : [3.14159,-1.5708,3.14159],
        "axis"   : [0,0,0],
        "limits" : [-3.141592653589793,3.141592653589793]    },
    {   "name"   : "InfraredL_sensor_fixedjoint",
        "type"   : "fixed",
        "parent" : "Head",
        "child"  : "LInfraRed_frame",
        "xyz"    : [0.0441,0.0257,0.0466],
        "rpy"    : [0,0,0],
        "axis"   : [0,0,0],
        "limits" : [-3.141592653589793,3.141592653589793]    },
    {   "name"   : "Gyrometer_sensor_fixedjoint",
        "type"   : "fixed",
        "parent" : "torso",
        "child"  : "ImuTorsoGyrometer_frame",
        "xyz"    : [-0.008,0.006,0.029],
        "rpy"    : [0,0,0],
        "axis"   : [0,0,0],
        "limits" : [-3.141592653589793,3.141592653589793]    },
    {   "name"   : "Head/Touch/Rear_sensor_fixedjoint",
        "type"   : "fixed",
        "parent" : "Head",
        "child"  : "HeadTouchRear_frame",
        "xyz"    : [-0.0257,0,0.1045],
        "rpy"    : [3.14159,-1.33319,-3.14159],
        "axis"   : [0,0,0],
        "limits" : [-3.141592653589793,3.141592653589793]    },
    {   "name"   : "Head/Touch/Middle_sensor_fixedjoint",
        "type"   : "fixed",
        "parent" : "Head",
        "child"  : "HeadTouchMiddle_frame",
        "xyz"    : [0.001,0,0.1099],
        "rpy"    : [3.14159,-1.57079,-3.14159],
        "axis"   : [0,0,0],
        "limits" : [-3.141592653589793,3.141592653589793]    },
    {   "name"   : "InfraredR_sensor_fixedjoint",
        "type"   : "fixed",
        "parent" : "Head",
        "child"  : "RInfraRed_frame",
        "xyz"    : [0.0441,-0.0257,0.0466],
        "rpy"    : [0,0,0],
        "axis"   : [0,0,0],
        "limits" : [-3.141592653589793,3.141592653589793]    },
    {   "name"   : "ChestBoard/Button_sensor_fixedjoint",
        "type"   : "fixed",
        "parent" : "torso",
        "child"  : "ChestButton_frame",
        "xyz"    : [0.049871,0.001588,0.055163],
        "rpy"    : [0,0,0],
        "axis"   : [0,0,0],
        "limits" : [-3.141592653589793,3.141592653589793]    },
    {   "name"   : "LFoot/Bumper/Left_sensor_fixedjoint",
        "type"   : "fixed",
        "parent" : "l_ankle",
        "child"  : "LFootBumperLeft_frame",
        "xyz"    : [0.0876,0.019,-0.0353],
        "rpy"    : [0,0,0],
        "axis"   : [0,0,0],
        "limits" : [-3.141592653589793,3.141592653589793]    },
    {   "name"   : "LHand/Touch/Right_sensor_fixedjoint",
        "type"   : "fixed",
        "parent" : "l_wrist",
        "child"  : "LHandTouchRight_frame",
        "xyz"    : [0.035,-0.025,0.0035],
        "rpy"    : [0,0,-1.5708],
        "axis"   : [0,0,0],
        "limits" : [-3.141592653589793,3.141592653589793]    },
    {   "name"   : "RFinger13",
        "type"   : "continuous",
        "parent" : "RFinger12_link",
        "child"  : "RFinger13_link",
        "xyz"    : [0.01436,0,0],
        "rpy"    : [0,0,-0.999899],
        "axis"   : [0,0,1.0],
        "limits" : [-3.141592653589793,3.141592653589793]    },
    {   "name"   : "RFinger12",
        "type"   : "continuous",
        "parent" : "RFinger11_link",
        "child"  : "RFinger12_link",
        "xyz"    : [0.01436,0,0],
        "rpy"    : [0,0,-0.999899],
        "axis"   : [0,0,1.0],
        "limits" : [-3.141592653589793,3.141592653589793]    },
    {   "name"   : "LFinger21",
        "type"   : "continuous",
        "parent" : "l_wrist",
        "child"  : "LFinger21_link",
        "xyz"    : [0.06907,-0.01157,-0.00304],
        "rpy"    : [1.25539,0.976662,-0.264067],
        "axis"   : [0,0,1.0],
        "limits" : [-3.141592653589793,3.141592653589793]    },
    {   "name"   : "LFinger13",
        "type"   : "continuous",
        "parent" : "LFinger12_link",
        "child"  : "LFinger13_link",
        "xyz"    : [0.01436,0,0],
        "rpy"    : [0,0,-0.999899],
        "axis"   : [0,0,1.0],
        "limits" : [-3.141592653589793,3.141592653589793]    },
    {   "name"   : "LFinger11",
        "type"   : "continuous",
        "parent" : "l_wrist",
        "child"  : "LFinger11_link",
        "xyz"    : [0.06907,0.01157,-0.00304],
        "rpy"    : [1.8862,0.976662,0.264067],
        "axis"   : [0,0,1.0],
        "limits" : [-3.141592653589793,3.141592653589793]    },
    {   "name"   : "RFinger22",
        "type"   : "continuous",
        "parent" : "RFinger21_link",
        "child"  : "RFinger22_link",
        "xyz"    : [0.01436,0,0],
        "rpy"    : [0,0,-0.999899],
        "axis"   : [0,0,1.0],
        "limits" : [-3.141592653589793,3.141592653589793]    },
    {   "name"   : "LFinger22",
        "type"   : "continuous",
        "parent" : "LFinger21_link",
        "child"  : "LFinger22_link",
        "xyz"    : [0.01436,0,0],
        "rpy"    : [0,0,-0.999899],
        "axis"   : [0,0,1.0],
        "limits" : [-3.141592653589793,3.141592653589793]    },
    {   "name"   : "RFinger21",
        "type"   : "continuous",
        "parent" : "r_wrist",
        "child"  : "RFinger21_link",
        "xyz"    : [0.06907,-0.01157,-0.00304],
        "rpy"    : [1.25539,0.976662,-0.264067],
        "axis"   : [0,0,1.0],
        "limits" : [-3.141592653589793,3.141592653589793]    },
    {   "name"   : "LFinger12",
        "type"   : "continuous",
        "parent" : "LFinger11_link",
        "child"  : "LFinger12_link",
        "xyz"    : [0.01436,0,0],
        "rpy"    : [0,0,-0.999899],
        "axis"   : [0,0,1.0],
        "limits" : [-3.141592653589793,3.141592653589793]    },
    {   "name"   : "RFinger23",
        "type"   : "continuous",
        "parent" : "RFinger22_link",
        "child"  : "RFinger23_link",
        "xyz"    : [0.01436,0,0],
        "rpy"    : [0,0,-0.999899],
        "axis"   : [0,0,1.0],
        "limits" : [-3.141592653589793,3.141592653589793]    },
    {   "name"   : "RFinger11",
        "type"   : "continuous",
        "parent" : "r_wrist",
        "child"  : "RFinger11_link",
        "xyz"    : [0.06907,0.01157,-0.00304],
        "rpy"    : [1.8862,0.976662,0.264067],
        "axis"   : [0,0,1.0],
        "limits" : [-3.141592653589793,3.141592653589793]    },
    {   "name"   : "LFinger23",
        "type"   : "continuous",
        "parent" : "LFinger22_link",
        "child"  : "LFinger23_link",
        "xyz"    : [0.01436,0,0],
        "rpy"    : [0,0,-0.999899],
        "axis"   : [0,0,1.0],
        "limits" : [-3.141592653589793,3.141592653589793]    },
    {   "name"   : "LThumb1",
        "type"   : "continuous",
        "parent" : "l_wrist",
        "child"  : "LThumb1_link",
        "xyz"    : [0.04895,0,-0.02638],
        "rpy"    : [-1.5708,0.0472984,-3.26826e-08],
        "axis"   : [0,0,1.0],
        "limits" : [-3.141592653589793,3.141592653589793]    },
    {   "name"   : "RThumb1",
        "type"   : "continuous",
        "parent" : "r_wrist",
        "child"  : "RThumb1_link",
        "xyz"    : [0.04895,0,-0.02638],
        "rpy"    : [-1.5708,0.0472984,-3.26826e-08],
        "axis"   : [0,0,1.0],
        "limits" : [-3.141592653589793,3.141592653589793]    },
    {   "name"   : "RThumb2",
        "type"   : "continuous",
        "parent" : "RThumb1_link",
        "child"  : "RThumb2_link",
        "xyz"    : [0.01436,0,0],
        "rpy"    : [0,0,-0.999899],
        "axis"   : [0,0,1.0],
        "limits" : [-3.141592653589793,3.141592653589793]    },
    {   "name"   : "LThumb2",
        "type"   : "continuous",
        "parent" : "LThumb1_link",
        "child"  : "LThumb2_link",
        "xyz"    : [0.01436,0,0],
        "rpy"    : [0,0,-0.999899],
        "axis"   : [0,0,1.0],
        "limits" : [-3.141592653589793,3.141592653589793]    }
    ],
"links" : [
    {   "name" : "Neck",
        "mesh"   : "nao_meshes/meshes/V40/HeadYaw.dae",
        "scale"  : [0.1,0.1,0.1],
        "cRad"   : 0.017945979789088597,
        "cOrg"   : [0.00012999202264561008,-4.877908429258607e-05,-0.012357145254269935],
        "cEnd"   : [-4.248138708987919e-05,1.5944703959671715e-05,0.01260396268487242]     },
    {   "name"   : "Head",
        "mesh"   : "nao_meshes/meshes/V40/HeadPitch.dae",
        "scale"  : [0.1,0.1,0.1],
        "cRad"   : 0.062010749801026166,
        "cOrg"   : [-0.0002594941689030299,-0.013450142286376488,0.055946270170501584],
        "cEnd"   : [0.00031976496978714663,0.013474088192277706,0.05546020750645142]     },
    {   "name"   : "gaze",
        "mesh"   : "__no visual__",
        "scale"  : [0.1,0.1,0.1],
        "cRad"   : 0.0,
        "cOrg"   : [0,0,0],
        "cEnd"   : [0,0,0]     },
    {   "name"   : "LPelvis",
        "mesh"   : "nao_meshes/meshes/V40/LHipYawPitch.dae",
        "scale"  : [0.1,0.1,0.1],
        "cRad"   : 0.03707338897502165,
        "cOrg"   : [-0.027640027912863855,-0.004949372332676546,0.011117733420384465],
        "cEnd"   : [0.00944423523438612,-0.009325228556213792,0.019972385657211354]     },
    {   "name"   : "LHip",
        "mesh"   : "nao_meshes/meshes/V40/LHipRoll.dae",
        "scale"  : [0.1,0.1,0.1],
        "cRad"   : 0.041271133696195686,
        "cOrg"   : [-0.01201593994011942,0.0009609665891230298,-0.010996346751593304],
        "cEnd"   : [-0.012085930344122153,8.797497724605599e-05,-0.011126471920383485]     },
    {   "name"   : "LThigh",
        "mesh"   : "nao_meshes/meshes/V40/LHipPitch.dae",
        "scale"  : [0.1,0.1,0.1],
        "cRad"   : 0.04885987723360987,
        "cOrg"   : [-0.004652423382477439,0.0018479308135228973,-0.02086362710665377],
        "cEnd"   : [0.012699732464973492,0.0008806684106015756,-0.10698340442635415]     },
    {   "name"   : "LTibia",
        "mesh"   : "nao_meshes/meshes/V40/LKneePitch.dae",
        "scale"  : [0.1,0.1,0.1],
        "cRad"   : 0.05538075583918483,
        "cOrg"   : [0.00028631766527452895,0.0025974662235884716,-0.08057726214903599],
        "cEnd"   : [0.0072578535584324365,0.0014402802108771614,-0.03235508802942565]     },
    {   "name"   : "LAnklePitch",
        "mesh"   : "nao_meshes/meshes/V40/LAnklePitch.dae",
        "scale"  : [0.1,0.1,0.1],
        "cRad"   : 0.04311601376796055,
        "cOrg"   : [-7.262923511422872e-05,-0.00185272727247325,0.013274843500779667],
        "cEnd"   : [-4.55981774203158e-05,0.0021381402932341984,0.01328024112733154]     },
    {   "name"   : "l_ankle",
        "mesh"   : "nao_meshes/meshes/V40/LAnkleRoll.dae",
        "scale"  : [0.1,0.1,0.1],
        "cRad"   : 0.05149231271733072,
        "cOrg"   : [-0.02637407375483304,0.004272674695621594,-0.021479701979889583],
        "cEnd"   : [0.05312814488579568,0.0025156591824039756,-0.027889374108590565]     },
    {   "name"   : "l_sole",
        "mesh"   : "__no visual__",
        "scale"  : [0.1,0.1,0.1],
        "cRad"   : 0.0,
        "cOrg"   : [0,0,0],
        "cEnd"   : [0,0,0]     },
    {   "name"   : "RPelvis",
        "mesh"   : "nao_meshes/meshes/V40/RHipYawPitch.dae",
        "scale"  : [0.1,0.1,0.1],
        "cRad"   : 0.05112966816245594,
        "cOrg"   : [-0.01339140953420461,0.006948803777436143,0.014180971899223044],
        "cEnd"   : [-0.013405459890953516,0.006384551374351361,0.014541220112889703]     },
    {   "name"   : "RHip",
        "mesh"   : "nao_meshes/meshes/V40/RHipRoll.dae",
        "scale"  : [0.1,0.1,0.1],
        "cRad"   : 0.04156721100530559,
        "cOrg"   : [-0.011602999936374115,-0.003374007249194889,-0.010973803263438732],
        "cEnd"   : [-0.01202133559262656,0.0018890739684338535,-0.011771625013718482]     },
    {   "name"   : "RThigh",
        "mesh"   : "nao_meshes/meshes/V40/RHipPitch.dae",
        "scale"  : [0.1,0.1,0.1],
        "cRad"   : 0.049629501968791914,
        "cOrg"   : [-0.0038301574173062016,-0.002434135534049503,-0.022121782784905158],
        "cEnd"   : [0.012428746400092755,-0.0002487542056023235,-0.11112717200423697]     },
    {   "name"   : "RTibia",
        "mesh"   : "nao_meshes/meshes/V40/RKneePitch.dae",
        "scale"  : [0.1,0.1,0.1],
        "cRad"   : 0.05549661779905281,
        "cOrg"   : [0.008999233485909109,-0.0013525641210329923,-0.020305242385446683],
        "cEnd"   : [0.0005943561142823881,-0.002617441389643412,-0.07746234700451253]     },
    {   "name"   : "RAnklePitch",
        "mesh"   : "nao_meshes/meshes/V40/RAnklePitch.dae",
        "scale"  : [0.1,0.1,0.1],
        "cRad"   : 0.04353816723283244,
        "cOrg"   : [0.0003490719297102349,-0.002789340174324194,0.013422616983780198],
        "cEnd"   : [0.000357601652354793,0.0022555489451473276,0.01345199455849966]     },
    {   "name"   : "r_ankle",
        "mesh"   : "nao_meshes/meshes/V40/RAnkleRoll.dae",
        "scale"  : [0.1,0.1,0.1],
        "cRad"   : 0.05269855543644894,
        "cOrg"   : [-0.02792918451942639,-0.0037968366725144413,-0.020149989175215457],
        "cEnd"   : [0.051950674642429195,-0.0017705326249087075,-0.02812415019477466]     },
    {   "name"   : "r_sole",
        "mesh"   : "__no visual__",
        "scale"  : [0.1,0.1,0.1],
        "cRad"   : 0.0,
        "cOrg"   : [0,0,0],
        "cEnd"   : [0,0,0]     },
    {   "name"   : "base_link",
        "mesh"   : "__no visual__",
        "scale"  : [0.1,0.1,0.1],
        "cRad"   : 0.0,
        "cOrg"   : [0,0,0],
        "cEnd"   : [0,0,0]     },
    {   "name"   : "torso",
        "mesh"   : "nao_meshes/meshes/V40/Torso.dae",
        "scale"  : [0.1,0.1,0.1],
        "cRad"   : 0.09114305816279628,
        "cOrg"   : [0.0017450197160509833,0.0027667089700351734,0.10120313369041561],
        "cEnd"   : [0.005584900855847171,-0.0018756952233594654,-0.004323285425552277]     },
    {   "name"   : "LShoulder",
        "mesh"   : "nao_meshes/meshes/V40/LShoulderPitch.dae",
        "scale"  : [0.1,0.1,0.1],
        "cRad"   : 0.050245066497406475,
        "cOrg"   : [-0.016057422955361583,-0.013708822119616455,-0.0003306102442302158],
        "cEnd"   : [-0.017445137468076327,-0.01974583738062192,-0.00035315238694315517]     },
    {   "name"   : "LBicep",
        "mesh"   : "nao_meshes/meshes/V40/LShoulderRoll.dae",
        "scale"  : [0.1,0.1,0.1],
        "cRad"   : 0.0451045954453585,
        "cOrg"   : [-0.008589328308570794,0.0017009830063613165,-0.00017868679423289725],
        "cEnd"   : [0.07678551606678286,0.011904240275285612,0.00059324737850266]     },
    {   "name"   : "LElbow",
        "mesh"   : "__no visual__",
        "scale"  : [0.1,0.1,0.1],
        "cRad"   : 0.0,
        "cOrg"   : [0,0,0],
        "cEnd"   : [0,0,0]     },
    {   "name"   : "LForeArm",
        "mesh"   : "nao_meshes/meshes/V40/LElbowRoll.dae",
        "scale"  : [0.1,0.1,0.1],
        "cRad"   : 0.029806030687988812,
        "cOrg"   : [0.006347793846206623,0.008792443841306084,0.0047771740518396805],
        "cEnd"   : [0.04306062667994255,-0.006366549048272791,-0.0014561220128038567]     },
    {   "name"   : "l_wrist",
        "mesh"   : "nao_meshes/meshes/V40/LWristYaw.dae",
        "scale"  : [0.1,0.1,0.1],
        "cRad"   : 0.034446745664836846,
        "cOrg"   : [0.020378686187905438,0.00015112540268953574,-0.006407325224229421],
        "cEnd"   : [0.06193563158380286,-0.0004924708712535544,0.010968590941395077]     },
    {   "name"   : "l_gripper",
        "mesh"   : "__no visual__",
        "scale"  : [0.1,0.1,0.1],
        "cRad"   : 0.0,
        "cOrg"   : [0,0,0],
        "cEnd"   : [0,0,0]     },
    {   "name"   : "RShoulder",
        "mesh"   : "nao_meshes/meshes/V40/RShoulderPitch.dae",
        "scale"  : [0.1,0.1,0.1],
        "cRad"   : 0.050153459816031976,
        "cOrg"   : [-0.016020185458292927,0.013913439977935958,0.0001675192265855532],
        "cEnd"   : [-0.017331264468327327,0.019742042933736607,0.0001741962183979344]     },
    {   "name"   : "RBicep",
        "mesh"   : "nao_meshes/meshes/V40/RShoulderRoll.dae",
        "scale"  : [0.1,0.1,0.1],
        "cRad"   : 0.045268935539035715,
        "cOrg"   : [-0.005754395204810938,-0.0023732549670101542,5.938834525069149e-05],
        "cEnd"   : [0.0771996163506008,-0.010665221568156642,0.0005855851133492137]     },
    {   "name"   : "RElbow",
        "mesh"   : "__no visual__",
        "scale"  : [0.1,0.1,0.1],
        "cRad"   : 0.0,
        "cOrg"   : [0,0,0],
        "cEnd"   : [0,0,0]     },
    {   "name"   : "RForeArm",
        "mesh"   : "nao_meshes/meshes/V40/RElbowRoll.dae",
        "scale"  : [0.1,0.1,0.1],
        "cRad"   : 0.029625323882225805,
        "cOrg"   : [0.006947565181609607,-0.008771804203675897,0.005414978827585917],
        "cEnd"   : [0.04509483686592081,0.006431957406053021,-0.0020925429409571327]     },
    {   "name"   : "r_wrist",
        "mesh"   : "nao_meshes/meshes/V40/RWristYaw.dae",
        "scale"  : [0.1,0.1,0.1],
        "cRad"   : 0.034446745664836846,
        "cOrg"   : [0.020378686187905438,0.00015112540268953574,-0.006407325224229421],
        "cEnd"   : [0.06193563158380286,-0.0004924708712535544,0.010968590941395077]     },
    {   "name"   : "r_gripper",
        "mesh"   : "__no visual__",
        "scale"  : [0.1,0.1,0.1],
        "cRad"   : 0.0,
        "cOrg"   : [0,0,0],
        "cEnd"   : [0,0,0]     },
    {   "name"   : "LFootBumperRight_frame",
        "mesh"   : "__no visual__",
        "scale"  : [0.1,0.1,0.1],
        "cRad"   : 0.0,
        "cOrg"   : [0,0,0],
        "cEnd"   : [0,0,0]     },
    {   "name"   : "RFsrRL_frame",
        "mesh"   : "__no visual__",
        "scale"  : [0.1,0.1,0.1],
        "cRad"   : 0.0,
        "cOrg"   : [0,0,0],
        "cEnd"   : [0,0,0]     },
    {   "name"   : "CameraBottom_optical_frame",
        "mesh"   : "__no visual__",
        "scale"  : [0.1,0.1,0.1],
        "cRad"   : 0.0,
        "cOrg"   : [0,0,0],
        "cEnd"   : [0,0,0]     },
    {   "name"   : "RFsrRR_frame",
        "mesh"   : "__no visual__",
        "scale"  : [0.1,0.1,0.1],
        "cRad"   : 0.0,
        "cOrg"   : [0,0,0],
        "cEnd"   : [0,0,0]     },
    {   "name"   : "LFsrFR_frame",
        "mesh"   : "__no visual__",
        "scale"  : [0.1,0.1,0.1],
        "cRad"   : 0.0,
        "cOrg"   : [0,0,0],
        "cEnd"   : [0,0,0]     },
    {   "name"   : "LHandTouchLeft_frame",
        "mesh"   : "__no visual__",
        "scale"  : [0.1,0.1,0.1],
        "cRad"   : 0.0,
        "cOrg"   : [0,0,0],
        "cEnd"   : [0,0,0]     },
    {   "name"   : "RFootBumperRight_frame",
        "mesh"   : "__no visual__",
        "scale"  : [0.1,0.1,0.1],
        "cRad"   : 0.0,
        "cOrg"   : [0,0,0],
        "cEnd"   : [0,0,0]     },
    {   "name"   : "RFsrFR_frame",
        "mesh"   : "__no visual__",
        "scale"  : [0.1,0.1,0.1],
        "cRad"   : 0.0,
        "cOrg"   : [0,0,0],
        "cEnd"   : [0,0,0]     },
    {   "name"   : "LFsrRR_frame",
        "mesh"   : "__no visual__",
        "scale"  : [0.1,0.1,0.1],
        "cRad"   : 0.0,
        "cOrg"   : [0,0,0],
        "cEnd"   : [0,0,0]     },
    {   "name"   : "ImuTorsoAccelerometer_frame",
        "mesh"   : "__no visual__",
        "scale"  : [0.1,0.1,0.1],
        "cRad"   : 0.0,
        "cOrg"   : [0,0,0],
        "cEnd"   : [0,0,0]     },
    {   "name"   : "HeadTouchFront_frame",
        "mesh"   : "__no visual__",
        "scale"  : [0.1,0.1,0.1],
        "cRad"   : 0.0,
        "cOrg"   : [0,0,0],
        "cEnd"   : [0,0,0]     },
    {   "name"   : "RFootBumperLeft_frame",
        "mesh"   : "__no visual__",
        "scale"  : [0.1,0.1,0.1],
        "cRad"   : 0.0,
        "cOrg"   : [0,0,0],
        "cEnd"   : [0,0,0]     },
    {   "name"   : "RSonar_frame",
        "mesh"   : "__no visual__",
        "scale"  : [0.1,0.1,0.1],
        "cRad"   : 0.0,
        "cOrg"   : [0,0,0],
        "cEnd"   : [0,0,0]     },
    {   "name"   : "RHandTouchRight_frame",
        "mesh"   : "__no visual__",
        "scale"  : [0.1,0.1,0.1],
        "cRad"   : 0.0,
        "cOrg"   : [0,0,0],
        "cEnd"   : [0,0,0]     },
    {   "name"   : "RHandTouchBack_frame",
        "mesh"   : "__no visual__",
        "scale"  : [0.1,0.1,0.1],
        "cRad"   : 0.0,
        "cOrg"   : [0,0,0],
        "cEnd"   : [0,0,0]     },
    {   "name"   : "RFsrFL_frame",
        "mesh"   : "__no visual__",
        "scale"  : [0.1,0.1,0.1],
        "cRad"   : 0.0,
        "cOrg"   : [0,0,0],
        "cEnd"   : [0,0,0]     },
    {   "name"   : "LSonar_frame",
        "mesh"   : "__no visual__",
        "scale"  : [0.1,0.1,0.1],
        "cRad"   : 0.0,
        "cOrg"   : [0,0,0],
        "cEnd"   : [0,0,0]     },
    {   "name"   : "LFsrFL_frame",
        "mesh"   : "__no visual__",
        "scale"  : [0.1,0.1,0.1],
        "cRad"   : 0.0,
        "cOrg"   : [0,0,0],
        "cEnd"   : [0,0,0]     },
    {   "name"   : "LFsrRL_frame",
        "mesh"   : "__no visual__",
        "scale"  : [0.1,0.1,0.1],
        "cRad"   : 0.0,
        "cOrg"   : [0,0,0],
        "cEnd"   : [0,0,0]     },
    {   "name"   : "RHandTouchLeft_frame",
        "mesh"   : "__no visual__",
        "scale"  : [0.1,0.1,0.1],
        "cRad"   : 0.0,
        "cOrg"   : [0,0,0],
        "cEnd"   : [0,0,0]     },
    {   "name"   : "CameraBottom_frame",
        "mesh"   : "__no visual__",
        "scale"  : [0.1,0.1,0.1],
        "cRad"   : 0.0,
        "cOrg"   : [0,0,0],
        "cEnd"   : [0,0,0]     },
    {   "name"   : "CameraTop_frame",
        "mesh"   : "__no visual__",
        "scale"  : [0.1,0.1,0.1],
        "cRad"   : 0.0,
        "cOrg"   : [0,0,0],
        "cEnd"   : [0,0,0]     },
    {   "name"   : "CameraTop_optical_frame",
        "mesh"   : "__no visual__",
        "scale"  : [0.1,0.1,0.1],
        "cRad"   : 0.0,
        "cOrg"   : [0,0,0],
        "cEnd"   : [0,0,0]     },
    {   "name"   : "LHandTouchBack_frame",
        "mesh"   : "__no visual__",
        "scale"  : [0.1,0.1,0.1],
        "cRad"   : 0.0,
        "cOrg"   : [0,0,0],
        "cEnd"   : [0,0,0]     },
    {   "name"   : "LInfraRed_frame",
        "mesh"   : "__no visual__",
        "scale"  : [0.1,0.1,0.1],
        "cRad"   : 0.0,
        "cOrg"   : [0,0,0],
        "cEnd"   : [0,0,0]     },
    {   "name"   : "ImuTorsoGyrometer_frame",
        "mesh"   : "__no visual__",
        "scale"  : [0.1,0.1,0.1],
        "cRad"   : 0.0,
        "cOrg"   : [0,0,0],
        "cEnd"   : [0,0,0]     },
    {   "name"   : "HeadTouchRear_frame",
        "mesh"   : "__no visual__",
        "scale"  : [0.1,0.1,0.1],
        "cRad"   : 0.0,
        "cOrg"   : [0,0,0],
        "cEnd"   : [0,0,0]     },
    {   "name"   : "HeadTouchMiddle_frame",
        "mesh"   : "__no visual__",
        "scale"  : [0.1,0.1,0.1],
        "cRad"   : 0.0,
        "cOrg"   : [0,0,0],
        "cEnd"   : [0,0,0]     },
    {   "name"   : "RInfraRed_frame",
        "mesh"   : "__no visual__",
        "scale"  : [0.1,0.1,0.1],
        "cRad"   : 0.0,
        "cOrg"   : [0,0,0],
        "cEnd"   : [0,0,0]     },
    {   "name"   : "ChestButton_frame",
        "mesh"   : "__no visual__",
        "scale"  : [0.1,0.1,0.1],
        "cRad"   : 0.0,
        "cOrg"   : [0,0,0],
        "cEnd"   : [0,0,0]     },
    {   "name"   : "LFootBumperLeft_frame",
        "mesh"   : "__no visual__",
        "scale"  : [0.1,0.1,0.1],
        "cRad"   : 0.0,
        "cOrg"   : [0,0,0],
        "cEnd"   : [0,0,0]     },
    {   "name"   : "LHandTouchRight_frame",
        "mesh"   : "__no visual__",
        "scale"  : [0.1,0.1,0.1],
        "cRad"   : 0.0,
        "cOrg"   : [0,0,0],
        "cEnd"   : [0,0,0]     },
    {   "name"   : "RFinger13_link",
        "mesh"   : "nao_meshes/meshes/V40/RFinger13.dae",
        "scale"  : [0.1,0.1,0.1],
        "cRad"   : 0.010953097470219556,
        "cOrg"   : [0.00726281938509613,-9.004284692443093e-05,-0.0004721016771641012],
        "cEnd"   : [0.007268602126905471,2.2866328814327712e-05,0.00027320112751164907]     },
    {   "name"   : "RFinger12_link",
        "mesh"   : "nao_meshes/meshes/V40/RFinger12.dae",
        "scale"  : [0.1,0.1,0.1],
        "cRad"   : 0.008221854632593683,
        "cOrg"   : [0.0020237543518262105,-0.00024742057509155455,-0.0008013089920810184],
        "cEnd"   : [0.011144143279031108,0.000359412248931016,0.001256388493442049]     },
    {   "name"   : "LFinger21_link",
        "mesh"   : "nao_meshes/meshes/V40/LFinger21.dae",
        "scale"  : [0.1,0.1,0.1],
        "cRad"   : 0.008268843231536567,
        "cOrg"   : [0.0033738500177268862,-2.778881813665113e-05,-0.00041850698675198136],
        "cEnd"   : [0.012517163483763145,-0.00012726472280721678,0.001675259877983365]     },
    {   "name"   : "LFinger13_link",
        "mesh"   : "nao_meshes/meshes/V40/LFinger13.dae",
        "scale"  : [0.1,0.1,0.1],
        "cRad"   : 0.010953102913768801,
        "cOrg"   : [0.00751033627371312,-0.00038320851248839456,-0.0005289114892336943],
        "cEnd"   : [0.007516573855491386,-0.0005049982066504709,0.0002750106785087111]     },
    {   "name"   : "LFinger11_link",
        "mesh"   : "nao_meshes/meshes/V40/LFinger11.dae",
        "scale"  : [0.1,0.1,0.1],
        "cRad"   : 0.008156215320736014,
        "cOrg"   : [0.003181304306366166,-9.543079921177437e-05,-0.0006877802503873016],
        "cEnd"   : [0.012299662639371458,-0.000679135874956725,0.0013511600542529198]     },
    {   "name"   : "RFinger22_link",
        "mesh"   : "nao_meshes/meshes/V40/RFinger22.dae",
        "scale"  : [0.1,0.1,0.1],
        "cRad"   : 0.008228869329330894,
        "cOrg"   : [0.0031945614439849515,-0.0003153774821916805,-0.0005265579488513529],
        "cEnd"   : [0.012181452993842993,-0.0005160326300548436,0.0016577296187347526]     },
    {   "name"   : "LFinger22_link",
        "mesh"   : "nao_meshes/meshes/V40/LFinger22.dae",
        "scale"  : [0.1,0.1,0.1],
        "cRad"   : 0.008221266945105509,
        "cOrg"   : [0.0030738742706265827,-7.822971829709436e-05,-0.0004663842821972578],
        "cEnd"   : [0.012454176421547527,-0.0001231708868521688,0.0017906795477377279]     },
    {   "name"   : "RFinger21_link",
        "mesh"   : "nao_meshes/meshes/V40/RFinger21.dae",
        "scale"  : [0.1,0.1,0.1],
        "cRad"   : 0.008145713389537476,
        "cOrg"   : [0.003426170032249089,0.00032309395111082713,-0.0008451987546172243],
        "cEnd"   : [0.012297533939995067,3.879902271740148e-05,0.0012719432172258718]     },
    {   "name"   : "LFinger12_link",
        "mesh"   : "nao_meshes/meshes/V40/LFinger12.dae",
        "scale"  : [0.1,0.1,0.1],
        "cRad"   : 0.00811079761237443,
        "cOrg"   : [0.0032334268934049526,-0.0004682650992985574,-0.0005756764049389884],
        "cEnd"   : [0.012341846879204116,-0.0007025890952264093,0.0016145959039286502]     },
    {   "name"   : "RFinger23_link",
        "mesh"   : "nao_meshes/meshes/V40/RFinger23.dae",
        "scale"  : [0.1,0.1,0.1],
        "cRad"   : 0.010887427043562378,
        "cOrg"   : [0.007609912353952568,-0.00029701559461623876,-0.00021842643694898207],
        "cEnd"   : [0.007609228433808919,-0.00040969729197020446,0.0004535870520912714]     },
    {   "name"   : "RFinger11_link",
        "mesh"   : "nao_meshes/meshes/V40/RFinger11.dae",
        "scale"  : [0.1,0.1,0.1],
        "cRad"   : 0.008285407269719413,
        "cOrg"   : [0.0035371568895975177,-0.0006486220205457929,-0.0007250825360269816],
        "cEnd"   : [0.012931359556492581,0.00021187876735668618,0.0013637891820474592]     },
    {   "name"   : "LFinger23_link",
        "mesh"   : "nao_meshes/meshes/V40/LFinger23.dae",
        "scale"  : [0.1,0.1,0.1],
        "cRad"   : 0.01095929985961361,
        "cOrg"   : [0.007594141695545449,-0.0003512900124910928,-0.00041251396344821534],
        "cEnd"   : [0.007600118611249061,-0.00014733836292770737,0.0006726547684212424]     },
    {   "name"   : "LThumb1_link",
        "mesh"   : "nao_meshes/meshes/V40/LThumb1.dae",
        "scale"  : [0.1,0.1,0.1],
        "cRad"   : 0.008104895776854698,
        "cOrg"   : [0.005381904493692797,0.00018482242461678622,-0.010060289911960148],
        "cEnd"   : [0.0035678249130487007,0.0003602246995187507,-0.0006613201423996623]     },
    {   "name"   : "RThumb1_link",
        "mesh"   : "nao_meshes/meshes/V40/RThumb1.dae",
        "scale"  : [0.1,0.1,0.1],
        "cRad"   : 0.008107170813791115,
        "cOrg"   : [0.004583561842072776,8.06519609673297e-05,-0.0003892072854871573],
        "cEnd"   : [0.006458121711409676,1.7460898255144662e-05,-0.0095129124465579]     },
    {   "name"   : "RThumb2_link",
        "mesh"   : "nao_meshes/meshes/V40/RThumb2.dae",
        "scale"  : [0.1,0.1,0.1],
        "cRad"   : 0.010885337352857752,
        "cOrg"   : [0.0030127893646584216,-0.0003006857608069929,-0.006983842773013901],
        "cEnd"   : [0.002179836286423235,-0.000282061345121898,-0.0074579241694867305]     },
    {   "name"   : "LThumb2_link",
        "mesh"   : "nao_meshes/meshes/V40/LThumb2.dae",
        "scale"  : [0.1,0.1,0.1],
        "cRad"   : 0.008127716363300485,
        "cOrg"   : [0.0006747193951035999,-8.946755597179238e-05,-0.005718081629384888],
        "cEnd"   : [0.0035931223021480486,9.928745267972979e-05,-0.010770594082557556]     }
    ]
}